{
  "lastUpdated": "2026-06-14T14:30:40.073Z",
  "expiresAt": "2026-06-14T15:30:40.073Z",
  "gameId": "29595",
  "gameName": "Dota 2",
  "source": "twitch-helix",
  "streams": [
    {
      "userLogin": "daxak",
      "userName": "Daxak",
      "title": "позор на мейне   !фонбет !бусти",
      "viewerCount": 5370,
      "language": "ru",
      "startedAt": "2026-06-14T09:44:41Z",
      "thumbnailUrl": "https://static-cdn.jtvnw.net/previews-ttv/live_user_daxak-{width}x{height}.jpg"
    },
    {
      "userLogin": "avice",
      "userName": "avice",
      "title": "15k mmr gameplay full tryhard !тимспиритжди !betboom !tg",
      "viewerCount": 3292,
      "language": "ru",
      "startedAt": "2026-06-14T13:42:38Z",
      "thumbnailUrl": "https://static-cdn.jtvnw.net/previews-ttv/live_user_avice-{width}x{height}.jpg"
    },
    {
      "userLogin": "qojqva",
      "userName": "qojqva",
      "title": "!SOCCER 16K CHALLENGE day2/60 !youtube !ig",
      "viewerCount": 3058,
      "language": "en",
      "startedAt": "2026-06-14T12:41:33Z",
      "thumbnailUrl": "https://static-cdn.jtvnw.net/previews-ttv/live_user_qojqva-{width}x{height}.jpg"
    },
    {
      "userLogin": "9class",
      "userName": "9Class",
      "title": "победитель 4 мажоров ✅Реплей - 2.5k✅Записи стримов на !boosty    // !tg",
      "viewerCount": 2026,
      "language": "ru",
      "startedAt": "2026-06-14T12:00:56Z",
      "thumbnailUrl": "https://static-cdn.jtvnw.net/previews-ttv/live_user_9class-{width}x{height}.jpg"
    },
    {
      "userLogin": "torontotokyo17",
      "userName": "TORONTOTOKYO17",
      "title": "mid gameplay?",
      "viewerCount": 1600,
      "language": "ru",
      "startedAt": "2026-06-14T12:01:13Z",
      "thumbnailUrl": "https://static-cdn.jtvnw.net/previews-ttv/live_user_torontotokyo17-{width}x{height}.jpg"
    },
    {
      "userLogin": "etoseregga",
      "userName": "etosereGGa",
      "title": "Расследование самого страшного читера в истории.",
      "viewerCount": 1325,
      "language": "ru",
      "startedAt": "2026-06-14T12:57:46Z",
      "thumbnailUrl": "https://static-cdn.jtvnw.net/previews-ttv/live_user_etoseregga-{width}x{height}.jpg"
    },
    {
      "userLogin": "mariostar666",
      "userName": "mariostar666",
      "title": "Я СЕЙЧАС ТРУСЫ СНИМУ",
      "viewerCount": 952,
      "language": "ru",
      "startedAt": "2026-06-14T13:46:04Z",
      "thumbnailUrl": "https://static-cdn.jtvnw.net/previews-ttv/live_user_mariostar666-{width}x{height}.jpg"
    },
    {
      "userLogin": "lawandaxd",
      "userName": "lawandaxd",
      "title": "🥵 АРКАНА за БАЛЛЫ | (на добром) [⚡ СИЛЬНЕЙШИЙ ⚡ ] 🛑 !РОЛЛ - АРКАНА НА ЦМКУ 🛑✔️ !тг !винлайн !spydota",
      "viewerCount": 884,
      "language": "ru",
      "startedAt": "2026-06-14T12:46:14Z",
      "thumbnailUrl": "https://static-cdn.jtvnw.net/previews-ttv/live_user_lawandaxd-{width}x{height}.jpg"
    },
    {
      "userLogin": "xibbe",
      "userName": "Xibbe",
      "title": "why does the donkey climb towards the top?",
      "viewerCount": 519,
      "language": "en",
      "startedAt": "2026-06-14T11:19:34Z",
      "thumbnailUrl": "https://static-cdn.jtvnw.net/previews-ttv/live_user_xibbe-{width}x{height}.jpg"
    },
    {
      "userLogin": "ueyo",
      "userName": "ueyo",
      "title": "РАЗБИРАЮ ВАШИ РЕПЛЕИ ЧЕКАЙТЕ ОПИСАНИЕ !тирлист",
      "viewerCount": 510,
      "language": "ru",
      "startedAt": "2026-06-14T10:15:59Z",
      "thumbnailUrl": "https://static-cdn.jtvnw.net/previews-ttv/live_user_ueyo-{width}x{height}.jpg"
    },
    {
      "userLogin": "justhatemeeecatq",
      "userName": "JUSTHATEMEEECATQ",
      "title": "200 ПОБЕД ПОДРЯД (УЖЕ 85)! АПАЮ ТОП 1 шторма ДБ и ОПЕНДОТЫ! ТОП 1 ШТОРМ СПИРИТ !буст !патии !донатх !коуч !тг !мейн",
      "viewerCount": 417,
      "language": "ru",
      "startedAt": "2026-06-14T11:59:49Z",
      "thumbnailUrl": "https://static-cdn.jtvnw.net/previews-ttv/live_user_justhatemeeecatq-{width}x{height}.jpg"
    },
    {
      "userLogin": "aliksunder",
      "userName": "AlikSunder",
      "title": "учусь на корах ☑️ !тг !mmr",
      "viewerCount": 380,
      "language": "ru",
      "startedAt": "2026-06-14T13:16:43Z",
      "thumbnailUrl": "https://static-cdn.jtvnw.net/previews-ttv/live_user_aliksunder-{width}x{height}.jpg"
    },
    {
      "userLogin": "nkt_01",
      "userName": "NkT_01",
      "title": "C 1000 ММР до 10000 за 45 дней(День 8) или врубаю вебку💀Я не фрик😊12 000 ММР POS 2😱!challenge !party !items !hero !!donate",
      "viewerCount": 348,
      "language": "ru",
      "startedAt": "2026-06-14T08:07:18Z",
      "thumbnailUrl": "https://static-cdn.jtvnw.net/previews-ttv/live_user_nkt_01-{width}x{height}.jpg"
    },
    {
      "userLogin": "good_mma",
      "userName": "good_mma",
      "title": "ку !tg !shop !mmr !pc !followage",
      "viewerCount": 342,
      "language": "ru",
      "startedAt": "2026-06-14T12:15:23Z",
      "thumbnailUrl": "https://static-cdn.jtvnw.net/previews-ttv/live_user_good_mma-{width}x{height}.jpg"
    },
    {
      "userLogin": "reira",
      "userName": "reira",
      "title": "турик с девочками от kitchendotacom",
      "viewerCount": 330,
      "language": "ru",
      "startedAt": "2026-06-14T09:09:50Z",
      "thumbnailUrl": "https://static-cdn.jtvnw.net/previews-ttv/live_user_reira-{width}x{height}.jpg"
    },
    {
      "userLogin": "raze1x6",
      "userName": "raze1x6",
      "title": "ЗАВИСТЬ✅ыаыа✅MATADORA✅НЕ ИГРОК❌ШЛЕМ СНЯТ❗В CUSTOM HERO CHAOS?😳✅ПОВЕЗЛО❌СЕГОДНЯ ЛАСТ НЕТВОРС?✅👹Я ФРИК!🦖и че вы ржете..😂 ПОКАЗЫВАЮ !tg",
      "viewerCount": 276,
      "language": "ru",
      "startedAt": "2026-06-14T13:23:41Z",
      "thumbnailUrl": "https://static-cdn.jtvnw.net/previews-ttv/live_user_raze1x6-{width}x{height}.jpg"
    },
    {
      "userLogin": "asds__games",
      "userName": "ASDS__GAMES",
      "title": "Dota 2 stream , 9000 mmr | dota with dad!",
      "viewerCount": 211,
      "language": "ru",
      "startedAt": "2026-06-14T09:36:31Z",
      "thumbnailUrl": "https://static-cdn.jtvnw.net/previews-ttv/live_user_asds__games-{width}x{height}.jpg"
    },
    {
      "userLogin": "rinlar",
      "userName": "Rinlar",
      "title": "1000 rank игрок)) позиция 1",
      "viewerCount": 194,
      "language": "ru",
      "startedAt": "2026-06-14T09:37:24Z",
      "thumbnailUrl": "https://static-cdn.jtvnw.net/previews-ttv/live_user_rinlar-{width}x{height}.jpg"
    },
    {
      "userLogin": "leviamur",
      "userName": "leviamur",
      "title": "cтримерсбатл  с рейруней",
      "viewerCount": 174,
      "language": "ru",
      "startedAt": "2026-06-14T09:07:01Z",
      "thumbnailUrl": "https://static-cdn.jtvnw.net/previews-ttv/live_user_leviamur-{width}x{height}.jpg"
    },
    {
      "userLogin": "kotvsapogege",
      "userName": "KoTvSapoGeGe",
      "title": "",
      "viewerCount": 150,
      "language": "ru",
      "startedAt": "2026-06-14T07:53:49Z",
      "thumbnailUrl": "https://static-cdn.jtvnw.net/previews-ttv/live_user_kotvsapogege-{width}x{height}.jpg"
    },
    {
      "userLogin": "prettysunraze",
      "userName": "prettysunraze",
      "title": "custom hero chaos chillin",
      "viewerCount": 144,
      "language": "ru",
      "startedAt": "2026-06-14T08:03:55Z",
      "thumbnailUrl": "https://static-cdn.jtvnw.net/previews-ttv/live_user_prettysunraze-{width}x{height}.jpg"
    },
    {
      "userLogin": "olagheparande",
      "userName": "olagheparande",
      "title": "Historye Sabz ya Ghermez? Masale ina ast",
      "viewerCount": 137,
      "language": "other",
      "startedAt": "2026-06-14T09:22:22Z",
      "thumbnailUrl": "https://static-cdn.jtvnw.net/previews-ttv/live_user_olagheparande-{width}x{height}.jpg"
    },
    {
      "userLogin": "csgopstv",
      "userName": "CSGOPSTV",
      "title": "ТУРНИР ОТ CSGOPOSITIVE по DOTA2 в формате 1x1 SOLO MID ! | @ARi4kaa !bet !tg !aim !турнир",
      "viewerCount": 134,
      "language": "ru",
      "startedAt": "2026-06-14T14:04:51Z",
      "thumbnailUrl": "https://static-cdn.jtvnw.net/previews-ttv/live_user_csgopstv-{width}x{height}.jpg"
    },
    {
      "userLogin": "deknoii888_v2",
      "userName": "deknoii888_v2",
      "title": "กับอิมบ้านเรา วันนี้เอาจริง",
      "viewerCount": 120,
      "language": "th",
      "startedAt": "2026-06-14T08:22:19Z",
      "thumbnailUrl": "https://static-cdn.jtvnw.net/previews-ttv/live_user_deknoii888_v2-{width}x{height}.jpg"
    },
    {
      "userLogin": "zuyzyan",
      "userName": "zuyzyan",
      "title": "Подготовка к Epl  трек 200р !tg",
      "viewerCount": 118,
      "language": "ru",
      "startedAt": "2026-06-14T09:13:05Z",
      "thumbnailUrl": "https://static-cdn.jtvnw.net/previews-ttv/live_user_zuyzyan-{width}x{height}.jpg"
    },
    {
      "userLogin": "bububu",
      "userName": "Bububu",
      "title": "Just for me",
      "viewerCount": 113,
      "language": "en",
      "startedAt": "2026-06-14T12:46:28Z",
      "thumbnailUrl": "https://static-cdn.jtvnw.net/previews-ttv/live_user_bububu-{width}x{height}.jpg"
    },
    {
      "userLogin": "meegera",
      "userName": "MEEGERA",
      "title": "❣️ ТВОЯ БЫВШАЯ ❣️",
      "viewerCount": 108,
      "language": "ru",
      "startedAt": "2026-06-14T11:54:50Z",
      "thumbnailUrl": "https://static-cdn.jtvnw.net/previews-ttv/live_user_meegera-{width}x{height}.jpg"
    },
    {
      "userLogin": "belonytv",
      "userName": "BelonyTV",
      "title": "ЛУЗ СТРІК ПРОДОВЖУЄТЬСЯ! СТАТА 4-14 13499 --> 10000 MMR до початку The International ✅POSITIVE STREAMER✅!збір",
      "viewerCount": 105,
      "language": "uk",
      "startedAt": "2026-06-14T09:03:31Z",
      "thumbnailUrl": "https://static-cdn.jtvnw.net/previews-ttv/live_user_belonytv-{width}x{height}.jpg"
    },
    {
      "userLogin": "chmdota",
      "userName": "CHMDota",
      "title": "🏆 Ultras Dota Pro League Season 55 | Elite Eclipse - Nethercore | BO3 | by skadi",
      "viewerCount": 104,
      "language": "ru",
      "startedAt": "2026-06-14T09:44:47Z",
      "thumbnailUrl": "https://static-cdn.jtvnw.net/previews-ttv/live_user_chmdota-{width}x{height}.jpg"
    },
    {
      "userLogin": "welskiy",
      "userName": "welskiy",
      "title": "путь с 9к до 8к за один стрим, стараюсь не руинить 67 !розыгрыш !руководство !воздух !пропеллер",
      "viewerCount": 93,
      "language": "ru",
      "startedAt": "2026-06-14T09:34:34Z",
      "thumbnailUrl": "https://static-cdn.jtvnw.net/previews-ttv/live_user_welskiy-{width}x{height}.jpg"
    },
    {
      "userLogin": "5uporte",
      "userName": "5uporte",
      "title": "Cyber Atleta|Alto Rendimento",
      "viewerCount": 89,
      "language": "pt",
      "startedAt": "2026-06-14T12:56:21Z",
      "thumbnailUrl": "https://static-cdn.jtvnw.net/previews-ttv/live_user_5uporte-{width}x{height}.jpg"
    },
    {
      "userLogin": "blastdota",
      "userName": "BLASTDota",
      "title": "HIGHLIGHTS RERUN: BLAST Slam VII",
      "viewerCount": 79,
      "language": "en",
      "startedAt": "2026-06-13T13:43:11Z",
      "thumbnailUrl": "https://static-cdn.jtvnw.net/previews-ttv/live_user_blastdota-{width}x{height}.jpg"
    },
    {
      "userLogin": "imartoy",
      "userName": "imartoy",
      "title": "ต้องมาแบกชายแท้ เหน่ย",
      "viewerCount": 77,
      "language": "th",
      "startedAt": "2026-06-14T09:37:40Z",
      "thumbnailUrl": "https://static-cdn.jtvnw.net/previews-ttv/live_user_imartoy-{width}x{height}.jpg"
    },
    {
      "userLogin": "w1spulya",
      "userName": "w1spulya",
      "title": "турик от kitchen.com",
      "viewerCount": 73,
      "language": "ru",
      "startedAt": "2026-06-14T09:06:46Z",
      "thumbnailUrl": "https://static-cdn.jtvnw.net/previews-ttv/live_user_w1spulya-{width}x{height}.jpg"
    },
    {
      "userLogin": "rainfall322",
      "userName": "rainfall322",
      "title": "Я НЕ АВИЧИ!!!",
      "viewerCount": 70,
      "language": "ru",
      "startedAt": "2026-06-14T13:15:15Z",
      "thumbnailUrl": "https://static-cdn.jtvnw.net/previews-ttv/live_user_rainfall322-{width}x{height}.jpg"
    },
    {
      "userLogin": "mexxess",
      "userName": "MeXXeSS",
      "title": "🎮 Dneska jedeme všechny role a uvidíme, co nám matchmaking nadělí. xD !točka😄🔥",
      "viewerCount": 66,
      "language": "cs",
      "startedAt": "2026-06-14T09:27:14Z",
      "thumbnailUrl": "https://static-cdn.jtvnw.net/previews-ttv/live_user_mexxess-{width}x{height}.jpg"
    },
    {
      "userLogin": "swoelllka",
      "userName": "swoelllka",
      "title": "Выхожу из абьюзивного ММР , вводите промокод DARSI на GTA5RP",
      "viewerCount": 62,
      "language": "ru",
      "startedAt": "2026-06-14T13:07:41Z",
      "thumbnailUrl": "https://static-cdn.jtvnw.net/previews-ttv/live_user_swoelllka-{width}x{height}.jpg"
    },
    {
      "userLogin": "johnnupro",
      "userName": "Johnnupro",
      "title": "✅ SUPPORT DIFF ✅ PREPARING FOR NEXT TI ✅ testing NEW META ✅",
      "viewerCount": 57,
      "language": "ru",
      "startedAt": "2026-06-14T06:20:15Z",
      "thumbnailUrl": "https://static-cdn.jtvnw.net/previews-ttv/live_user_johnnupro-{width}x{height}.jpg"
    },
    {
      "userLogin": "krasavcheeeg46",
      "userName": "krasavcheeeg46",
      "title": "Dota 2  Добить 1000 ммр",
      "viewerCount": 52,
      "language": "ru",
      "startedAt": "2026-06-14T14:04:25Z",
      "thumbnailUrl": "https://static-cdn.jtvnw.net/previews-ttv/live_user_krasavcheeeg46-{width}x{height}.jpg"
    },
    {
      "userLogin": "professor__tv",
      "userName": "ProFessoR__TV",
      "title": "Летс гооооооооооо",
      "viewerCount": 52,
      "language": "uk",
      "startedAt": "2026-06-14T08:27:10Z",
      "thumbnailUrl": "https://static-cdn.jtvnw.net/previews-ttv/live_user_professor__tv-{width}x{height}.jpg"
    },
    {
      "userLogin": "bone7",
      "userName": "bOne7",
      "title": "Adventures of a ranked OFFLANE noob ( 12,341 MMR - #937 )",
      "viewerCount": 51,
      "language": "en",
      "startedAt": "2026-06-14T09:39:09Z",
      "thumbnailUrl": "https://static-cdn.jtvnw.net/previews-ttv/live_user_bone7-{width}x{height}.jpg"
    },
    {
      "userLogin": "esl_dota2",
      "userName": "ESL_DOTA2",
      "title": "HIGHLIGHTS: PARIVISION vs. Team Falcons - DreamLeague S29",
      "viewerCount": 51,
      "language": "en",
      "startedAt": "2026-06-13T22:04:52Z",
      "thumbnailUrl": "https://static-cdn.jtvnw.net/previews-ttv/live_user_esl_dota2-{width}x{height}.jpg"
    },
    {
      "userLogin": "waveafterwave2ndlife",
      "userName": "waveafterwave2ndlife",
      "title": "!награды !meme !заказ !tg !boosty",
      "viewerCount": 49,
      "language": "ru",
      "startedAt": "2026-06-14T14:00:53Z",
      "thumbnailUrl": "https://static-cdn.jtvnw.net/previews-ttv/live_user_waveafterwave2ndlife-{width}x{height}.jpg"
    },
    {
      "userLogin": "saintkaiser1x6",
      "userName": "saintkaiser1x6",
      "title": "ТЫ МОЯ ПОЛОВИНА <3",
      "viewerCount": 48,
      "language": "ru",
      "startedAt": "2026-06-14T13:56:42Z",
      "thumbnailUrl": "https://static-cdn.jtvnw.net/previews-ttv/live_user_saintkaiser1x6-{width}x{height}.jpg"
    },
    {
      "userLogin": "sunfamejr",
      "userName": "SunFameJr",
      "title": "Wyvern 20k matches | YouTube - 21:9, Twitch - 16:9",
      "viewerCount": 46,
      "language": "ru",
      "startedAt": "2026-06-14T11:08:39Z",
      "thumbnailUrl": "https://static-cdn.jtvnw.net/previews-ttv/live_user_sunfamejr-{width}x{height}.jpg"
    },
    {
      "userLogin": "alicecartoon",
      "userName": "alicecartoon",
      "title": "♥ЖЕНЩИНА♥",
      "viewerCount": 44,
      "language": "ru",
      "startedAt": "2026-06-14T11:21:37Z",
      "thumbnailUrl": "https://static-cdn.jtvnw.net/previews-ttv/live_user_alicecartoon-{width}x{height}.jpg"
    },
    {
      "userLogin": "mrb1g1k",
      "userName": "mrb1g1k",
      "title": "...",
      "viewerCount": 44,
      "language": "th",
      "startedAt": "2026-06-14T10:30:25Z",
      "thumbnailUrl": "https://static-cdn.jtvnw.net/previews-ttv/live_user_mrb1g1k-{width}x{height}.jpg"
    },
    {
      "userLogin": "semserrrr",
      "userName": "SemserrrR",
      "title": "Pma winning stream - Lil $em",
      "viewerCount": 43,
      "language": "el",
      "startedAt": "2026-06-14T09:27:08Z",
      "thumbnailUrl": "https://static-cdn.jtvnw.net/previews-ttv/live_user_semserrrr-{width}x{height}.jpg"
    },
    {
      "userLogin": "arteezysbastark",
      "userName": "arteezysbastark",
      "title": "14500ммр добро пожаловать в русский съем квартир #играюнамете 💀💀  tg: https://t.me/meowspreader",
      "viewerCount": 43,
      "language": "ru",
      "startedAt": "2026-06-14T12:42:40Z",
      "thumbnailUrl": "https://static-cdn.jtvnw.net/previews-ttv/live_user_arteezysbastark-{width}x{height}.jpg"
    },
    {
      "userLogin": "anaxmaia",
      "userName": "anaxmaia",
      "title": "LIVE DO BIGODAX. DOTINHA RESENHA COM OS AMIGOS. QUEM SABE MAIS TARDE PUBS NA SMURF 8K OU CINETIRIRIRICA !pix !coach",
      "viewerCount": 43,
      "language": "pt",
      "startedAt": "2026-06-14T00:08:01Z",
      "thumbnailUrl": "https://static-cdn.jtvnw.net/previews-ttv/live_user_anaxmaia-{width}x{height}.jpg"
    },
    {
      "userLogin": "positive_player12",
      "userName": "positive_player12",
      "title": "Auto Gladiators S10 Season Gладиаторы !гайд !tg !билды !YouTube",
      "viewerCount": 43,
      "language": "ru",
      "startedAt": "2026-06-14T11:55:37Z",
      "thumbnailUrl": "https://static-cdn.jtvnw.net/previews-ttv/live_user_positive_player12-{width}x{height}.jpg"
    },
    {
      "userLogin": "dota2_maincast",
      "userName": "dota2_maincast",
      "title": "[UA] RERUN: NAVI at EWC 2026 WEU CQ | All Matches",
      "viewerCount": 40,
      "language": "uk",
      "startedAt": "2026-06-13T14:09:11Z",
      "thumbnailUrl": "https://static-cdn.jtvnw.net/previews-ttv/live_user_dota2_maincast-{width}x{height}.jpg"
    },
    {
      "userLogin": "d1man41g",
      "userName": "d1man41g",
      "title": "14k паби фулл фокус НОВА ЛЕГЕНДА",
      "viewerCount": 40,
      "language": "uk",
      "startedAt": "2026-06-14T11:59:38Z",
      "thumbnailUrl": "https://static-cdn.jtvnw.net/previews-ttv/live_user_d1man41g-{width}x{height}.jpg"
    },
    {
      "userLogin": "tishinasaturna",
      "userName": "tishinasaturna",
      "title": "сон под тенью дерева | !тг !пати !рулетка",
      "viewerCount": 38,
      "language": "ru",
      "startedAt": "2026-06-14T10:51:15Z",
      "thumbnailUrl": "https://static-cdn.jtvnw.net/previews-ttv/live_user_tishinasaturna-{width}x{height}.jpg"
    },
    {
      "userLogin": "wwoonniiee",
      "userName": "wwoonniiee",
      "title": "If you have a heart attack, just attack back",
      "viewerCount": 36,
      "language": "en",
      "startedAt": "2026-06-14T13:09:53Z",
      "thumbnailUrl": "https://static-cdn.jtvnw.net/previews-ttv/live_user_wwoonniiee-{width}x{height}.jpg"
    },
    {
      "userLogin": "8ert8",
      "userName": "8ert8",
      "title": "руки пар3заныыыыы летом # ＞＜",
      "viewerCount": 36,
      "language": "ru",
      "startedAt": "2026-06-14T13:14:35Z",
      "thumbnailUrl": "https://static-cdn.jtvnw.net/previews-ttv/live_user_8ert8-{width}x{height}.jpg"
    },
    {
      "userLogin": "wh1tehell",
      "userName": "Wh1teHell",
      "title": "✅ЛУЗ - 20 ОТЖИМАНИЙ✅В мире животных✅Делаем новый мейн✅!тг !буст !пати",
      "viewerCount": 34,
      "language": "ru",
      "startedAt": "2026-06-14T06:53:30Z",
      "thumbnailUrl": "https://static-cdn.jtvnw.net/previews-ttv/live_user_wh1tehell-{width}x{height}.jpg"
    },
    {
      "userLogin": "flaminkovt",
      "userName": "FlaminkoVT",
      "title": "aaaaaaaaaaaaaaaaaaaaaa",
      "viewerCount": 33,
      "language": "en",
      "startedAt": "2026-06-14T14:02:50Z",
      "thumbnailUrl": "https://static-cdn.jtvnw.net/previews-ttv/live_user_flaminkovt-{width}x{height}.jpg"
    },
    {
      "userLogin": "vol1ker",
      "userName": "vol1ker",
      "title": "<(-_-)>",
      "viewerCount": 33,
      "language": "ru",
      "startedAt": "2026-06-14T13:08:18Z",
      "thumbnailUrl": "https://static-cdn.jtvnw.net/previews-ttv/live_user_vol1ker-{width}x{height}.jpg"
    },
    {
      "userLogin": "klos_dota2",
      "userName": "KloS_Dota2",
      "title": "В ПОИСКАХ КОНТЕНТА ПО ДОТЕ 2 🔴 LIVE🔴 THRONE DUST MIDAS 🟢",
      "viewerCount": 33,
      "language": "ru",
      "startedAt": "2026-06-14T13:14:53Z",
      "thumbnailUrl": "https://static-cdn.jtvnw.net/previews-ttv/live_user_klos_dota2-{width}x{height}.jpg"
    },
    {
      "userLogin": "senpaimarko",
      "userName": "senpaimarko",
      "title": "КалибровОчка | Научите играть,либо дайте нормальный тиммейтов",
      "viewerCount": 32,
      "language": "ru",
      "startedAt": "2026-06-14T11:14:43Z",
      "thumbnailUrl": "https://static-cdn.jtvnw.net/previews-ttv/live_user_senpaimarko-{width}x{height}.jpg"
    },
    {
      "userLogin": "sowiiaxi_",
      "userName": "sowiiaxi_",
      "title": "можно пати рейт за баллы ✅ !tg !пати Китик - @bankanyashka 🤍",
      "viewerCount": 32,
      "language": "ru",
      "startedAt": "2026-06-14T12:56:13Z",
      "thumbnailUrl": "https://static-cdn.jtvnw.net/previews-ttv/live_user_sowiiaxi_-{width}x{height}.jpg"
    },
    {
      "userLogin": "gendeezzy1337",
      "userName": "gendeezzy1337",
      "title": "Custom hero chaos,играю со всеми.Чуть позже Ancient Arena !слот!челенджи!курсовые",
      "viewerCount": 31,
      "language": "ru",
      "startedAt": "2026-06-14T11:38:10Z",
      "thumbnailUrl": "https://static-cdn.jtvnw.net/previews-ttv/live_user_gendeezzy1337-{width}x{height}.jpg"
    },
    {
      "userLogin": "lepta_one",
      "userName": "lepta_one",
      "title": "Поменял акич. С 0 ДО Титана на герое с нижней строчки винрейта дб(43%).Старт(1) Сейчас(4231).",
      "viewerCount": 31,
      "language": "ru",
      "startedAt": "2026-06-14T12:47:27Z",
      "thumbnailUrl": "https://static-cdn.jtvnw.net/previews-ttv/live_user_lepta_one-{width}x{height}.jpg"
    },
    {
      "userLogin": "superlasca",
      "userName": "SuperLasca",
      "title": "Road to Ancient... powered by tilt și feeding! xD",
      "viewerCount": 31,
      "language": "ro",
      "startedAt": "2026-06-14T10:10:32Z",
      "thumbnailUrl": "https://static-cdn.jtvnw.net/previews-ttv/live_user_superlasca-{width}x{height}.jpg"
    },
    {
      "userLogin": "oleg_wroom_wroom",
      "userName": "OLEG_WROOM_WROOM",
      "title": "джага",
      "viewerCount": 30,
      "language": "ru",
      "startedAt": "2026-06-14T10:52:32Z",
      "thumbnailUrl": "https://static-cdn.jtvnw.net/previews-ttv/live_user_oleg_wroom_wroom-{width}x{height}.jpg"
    },
    {
      "userLogin": "berserk_dota2_league",
      "userName": "Berserk_Dota2_League",
      "title": "Berserk League 14/06/2026 - Afternoon Session",
      "viewerCount": 30,
      "language": "en",
      "startedAt": "2026-06-14T13:55:12Z",
      "thumbnailUrl": "https://static-cdn.jtvnw.net/previews-ttv/live_user_berserk_dota2_league-{width}x{height}.jpg"
    },
    {
      "userLogin": "meks120kg",
      "userName": "meks120kg",
      "title": "ВЫЖИВАНИЕ ЛУЧШЕГО В МИРЕ ДЕНЬ 16 [ЗАВТРАК 13-00]",
      "viewerCount": 30,
      "language": "ru",
      "startedAt": "2026-06-13T20:20:30Z",
      "thumbnailUrl": "https://static-cdn.jtvnw.net/previews-ttv/live_user_meks120kg-{width}x{height}.jpg"
    },
    {
      "userLogin": "xxheartblade",
      "userName": "xxheartblade",
      "title": "ROAD TO 15.000 MMR |  БЕЗ ОШИБОК И СМЕРТЕЙ  | ПОЯСНЯЮ ЗА МИКРО",
      "viewerCount": 29,
      "language": "ru",
      "startedAt": "2026-06-14T13:35:12Z",
      "thumbnailUrl": "https://static-cdn.jtvnw.net/previews-ttv/live_user_xxheartblade-{width}x{height}.jpg"
    },
    {
      "userLogin": "magnat_donatovich",
      "userName": "MAGNAT_DONATOVICH",
      "title": "🏆🏆ЧЕЛЛЕНДЖ UP ТИТАНА - ДО КОНЦУ ЛЕТА. 🏆ДЕНЬ 1/78. 🏆ММР 4786/5620🏆🏆  !tg !donate !mmr",
      "viewerCount": 28,
      "language": "ru",
      "startedAt": "2026-06-14T12:05:26Z",
      "thumbnailUrl": "https://static-cdn.jtvnw.net/previews-ttv/live_user_magnat_donatovich-{width}x{height}.jpg"
    },
    {
      "userLogin": "ev1lbstrd",
      "userName": "ev1lbstrd",
      "title": "morph enjoyer  9000 carry 30 lancer/morph",
      "viewerCount": 28,
      "language": "ru",
      "startedAt": "2026-06-14T13:59:10Z",
      "thumbnailUrl": "https://static-cdn.jtvnw.net/previews-ttv/live_user_ev1lbstrd-{width}x{height}.jpg"
    },
    {
      "userLogin": "zangear777",
      "userName": "zangear777",
      "title": "новый стример, хайп, учеба, скил, тильт, от нуля то титяна",
      "viewerCount": 28,
      "language": "ru",
      "startedAt": "2026-06-14T12:04:34Z",
      "thumbnailUrl": "https://static-cdn.jtvnw.net/previews-ttv/live_user_zangear777-{width}x{height}.jpg"
    },
    {
      "userLogin": "dobryak_streamer",
      "userName": "dobryak_streamer",
      "title": "Заказ героев!❄️💖 Дота с Добрыней!",
      "viewerCount": 28,
      "language": "ru",
      "startedAt": "2026-06-14T09:16:41Z",
      "thumbnailUrl": "https://static-cdn.jtvnw.net/previews-ttv/live_user_dobryak_streamer-{width}x{height}.jpg"
    },
    {
      "userLogin": "kurnikmi",
      "userName": "kurnikmi",
      "title": "Каждый совет из чата ОБЯЗАТЕЛЕН к исполнению",
      "viewerCount": 27,
      "language": "ru",
      "startedAt": "2026-06-14T12:04:34Z",
      "thumbnailUrl": "https://static-cdn.jtvnw.net/previews-ttv/live_user_kurnikmi-{width}x{height}.jpg"
    },
    {
      "userLogin": "nukesyz",
      "userName": "NukeSyz",
      "title": "กลิ่นปลาสลิดติดไปทั้งตัว 0 - 0 .. !Donate !Sub",
      "viewerCount": 26,
      "language": "th",
      "startedAt": "2026-06-14T12:59:00Z",
      "thumbnailUrl": "https://static-cdn.jtvnw.net/previews-ttv/live_user_nukesyz-{width}x{height}.jpg"
    },
    {
      "userLogin": "trypovo333ka",
      "userName": "trypovo333ka",
      "title": "Комментим полуфинал-финал лоу птс турнира на пфб. 10-14 ЗАДЕРЖКА 1.5 минуты.",
      "viewerCount": 26,
      "language": "ru",
      "startedAt": "2026-06-14T13:19:18Z",
      "thumbnailUrl": "https://static-cdn.jtvnw.net/previews-ttv/live_user_trypovo333ka-{width}x{height}.jpg"
    },
    {
      "userLogin": "hknst",
      "userName": "HKNST",
      "title": "Ranked !sr kanavapisteillä",
      "viewerCount": 26,
      "language": "fi",
      "startedAt": "2026-06-14T11:00:42Z",
      "thumbnailUrl": "https://static-cdn.jtvnw.net/previews-ttv/live_user_hknst-{width}x{height}.jpg"
    },
    {
      "userLogin": "hloechkaaa",
      "userName": "hloechkaaa",
      "title": "всем нефорами привет, а скучным нормисам желаю поскорее найти себя",
      "viewerCount": 25,
      "language": "ru",
      "startedAt": "2026-06-14T13:17:12Z",
      "thumbnailUrl": "https://static-cdn.jtvnw.net/previews-ttv/live_user_hloechkaaa-{width}x{height}.jpg"
    },
    {
      "userLogin": "blessykirin",
      "userName": "blessykirin",
      "title": "Буст | 50 РУБ = 1 победа | KEz / INVOKER FP !пати | !donate | !tg Буст бесплатно за регу Betboom",
      "viewerCount": 25,
      "language": "ru",
      "startedAt": "2026-06-14T13:06:25Z",
      "thumbnailUrl": "https://static-cdn.jtvnw.net/previews-ttv/live_user_blessykirin-{width}x{height}.jpg"
    },
    {
      "userLogin": "skylightsesh",
      "userName": "skylightsesh",
      "title": "12000mid/12 дней до др/15 дней до армии))) !трек !сборка !онлифанс",
      "viewerCount": 25,
      "language": "ru",
      "startedAt": "2026-06-14T10:16:25Z",
      "thumbnailUrl": "https://static-cdn.jtvnw.net/previews-ttv/live_user_skylightsesh-{width}x{height}.jpg"
    },
    {
      "userLogin": "serbianbutchertv",
      "userName": "SerbianButcherTV",
      "title": "Dota Auto Chess & Dota 2!",
      "viewerCount": 23,
      "language": "en",
      "startedAt": "2026-06-14T13:00:06Z",
      "thumbnailUrl": "https://static-cdn.jtvnw.net/previews-ttv/live_user_serbianbutchertv-{width}x{height}.jpg"
    },
    {
      "userLogin": "laque",
      "userName": "laque",
      "title": "чем больше город, тем сильнее одиночество",
      "viewerCount": 22,
      "language": "ru",
      "startedAt": "2026-06-14T09:32:58Z",
      "thumbnailUrl": "https://static-cdn.jtvnw.net/previews-ttv/live_user_laque-{width}x{height}.jpg"
    },
    {
      "userLogin": "anynhageek",
      "userName": "AnynhaGeek",
      "title": "Drink live parte 2 / TURBO+ RANKED/ Cogite apoiar a stream !pix !comandos @g4tts",
      "viewerCount": 22,
      "language": "pt",
      "startedAt": "2026-06-13T11:57:29Z",
      "thumbnailUrl": "https://static-cdn.jtvnw.net/previews-ttv/live_user_anynhageek-{width}x{height}.jpg"
    },
    {
      "userLogin": "element_forzense",
      "userName": "element_forzense",
      "title": "Тверской 5vs5 WinstrikeCup по Dota2|||DAY 2|||NAOTARO vs BANDA SAMIKA||| GRAND FINAL 1-0",
      "viewerCount": 21,
      "language": "ru",
      "startedAt": "2026-06-14T07:12:22Z",
      "thumbnailUrl": "https://static-cdn.jtvnw.net/previews-ttv/live_user_element_forzense-{width}x{height}.jpg"
    },
    {
      "userLogin": "askoltbaby",
      "userName": "askoltbaby",
      "title": "Комментим лоу ммр турнир на PARTY FOR BOOST!! 7500 ММР - ПОТОЛОК! Задержка 90 сек, отвечаем на чатик, комментим пред-полуфинал",
      "viewerCount": 21,
      "language": "ru",
      "startedAt": "2026-06-14T13:19:18Z",
      "thumbnailUrl": "https://static-cdn.jtvnw.net/previews-ttv/live_user_askoltbaby-{width}x{height}.jpg"
    },
    {
      "userLogin": "slyzeeeeeeeeee",
      "userName": "SLyZeeeeeeeeee",
      "title": "sunday wins!",
      "viewerCount": 20,
      "language": "el",
      "startedAt": "2026-06-14T12:27:26Z",
      "thumbnailUrl": "https://static-cdn.jtvnw.net/previews-ttv/live_user_slyzeeeeeeeeee-{width}x{height}.jpg"
    },
    {
      "userLogin": "cmexgrex",
      "userName": "cmexgrex",
      "title": "мид лион на лоу ммр  | !tg !коуч !steam",
      "viewerCount": 20,
      "language": "ru",
      "startedAt": "2026-06-14T12:45:37Z",
      "thumbnailUrl": "https://static-cdn.jtvnw.net/previews-ttv/live_user_cmexgrex-{width}x{height}.jpg"
    },
    {
      "userLogin": "murmuwer",
      "userName": "murmuwer",
      "title": "привет, я новенькая >⩊<",
      "viewerCount": 19,
      "language": "ru",
      "startedAt": "2026-06-14T14:12:51Z",
      "thumbnailUrl": "https://static-cdn.jtvnw.net/previews-ttv/live_user_murmuwer-{width}x{height}.jpg"
    },
    {
      "userLogin": "cocojambic_g",
      "userName": "CocoJambic_G",
      "title": "Секрет, о котором молчат все...",
      "viewerCount": 19,
      "language": "ru",
      "startedAt": "2026-06-14T11:18:43Z",
      "thumbnailUrl": "https://static-cdn.jtvnw.net/previews-ttv/live_user_cocojambic_g-{width}x{height}.jpg"
    },
    {
      "userLogin": "trinity_zxc",
      "userName": "trinity_zxc",
      "title": "trinity",
      "viewerCount": 17,
      "language": "en",
      "startedAt": "2026-06-14T09:12:35Z",
      "thumbnailUrl": "https://static-cdn.jtvnw.net/previews-ttv/live_user_trinity_zxc-{width}x{height}.jpg"
    },
    {
      "userLogin": "frangie",
      "userName": "Frangie",
      "title": "OCE IN-HOUSE - !leaderboard / From Griefmaster to Beastmaster Week 2 (Sun) - Zookeeper Arc - Frangie #Kingslayer",
      "viewerCount": 16,
      "language": "en",
      "startedAt": "2026-06-14T08:38:49Z",
      "thumbnailUrl": "https://static-cdn.jtvnw.net/previews-ttv/live_user_frangie-{width}x{height}.jpg"
    },
    {
      "userLogin": "bay4nica",
      "userName": "BAY4NICA",
      "title": ". MMR, Меин 13к Нашел Имбу Патча 7.41. Top 3 poss На Титянах. А где Пудж ( Сегодня точно без тильта))",
      "viewerCount": 13,
      "language": "ru",
      "startedAt": "2026-06-13T20:09:50Z",
      "thumbnailUrl": "https://static-cdn.jtvnw.net/previews-ttv/live_user_bay4nica-{width}x{height}.jpg"
    },
    {
      "userLogin": "gordeevskyi_xleb",
      "userName": "GORDEEVSKYI_XLEB",
      "title": "ДНЕВНОЙ ВРЫВ В ДОТА 2, РЕЙТИНГ + КАСТОМКА",
      "viewerCount": 13,
      "language": "ru",
      "startedAt": "2026-06-14T11:31:54Z",
      "thumbnailUrl": "https://static-cdn.jtvnw.net/previews-ttv/live_user_gordeevskyi_xleb-{width}x{height}.jpg"
    },
    {
      "userLogin": "legrot",
      "userName": "LeGroT",
      "title": "Custom hero chaos lobby",
      "viewerCount": 10,
      "language": "ru",
      "startedAt": "2026-06-14T13:25:30Z",
      "thumbnailUrl": "https://static-cdn.jtvnw.net/previews-ttv/live_user_legrot-{width}x{height}.jpg"
    }
  ]
}
